yaspi/yaspi.py
yaspi/misc/minimal_ray_example.py
yaspi/templates/cpu-proc/master.sh
yaspi/templates/cpu-proc/template.sh
yaspi/templates/gpu-proc/master.sh
yaspi/templates/gpu-proc/template.sh
yaspi/templates/ray/ray-master.sh
yaspi/templates/ray/ray-sbatch.sh
yaspi/templates/ray/start-ray-head-node.sh
yaspi/templates/ray/start-ray-worker-node.sh
yaspi-0.0.8.dist-info/METADATA
yaspi-0.0.8.dist-info/WHEEL
yaspi-0.0.8.dist-info/entry_points.txt
yaspi-0.0.8.dist-info/top_level.txt
yaspi-0.0.8.dist-info/RECORD
