Metadata-Version: 2.1
Name: yaspi
Version: 0.0.8
Summary: Yet Another Slurm Python Interface
Home-page: https://github.com/albanie/yaspi
Author: Samuel Albanie
License: UNKNOWN
Platform: UNKNOWN
Classifier: Programming Language :: Python :: 3.7
Classifier: License :: OSI Approved :: MIT License
Classifier: Operating System :: POSIX :: Linux
Requires-Python: >=3.7
Requires-Dist: watchlogs
Requires-Dist: beartype (>=0.7.1)
